pagemeta/__init__.py
pagemeta/admin.py
pagemeta/apps.py
pagemeta/middleware.py
pagemeta/models.py
pagemeta/requests.py
pagemeta/tests.py
pagemeta/utils.py
pagemeta/views.py
pagemeta/migrations/0001_initial.py
pagemeta/migrations/0002_auto_20220917_0623.py
pagemeta/migrations/0003_auto_20221002_0903.py
pagemeta/migrations/0004_auto_20221002_1207.py
pagemeta/migrations/__init__.py
pagemeta/templates/pagemeta/meta.html
pagemeta_example/__init__.py
pagemeta_example/admin.py
pagemeta_example/apps.py
pagemeta_example/models.py
pagemeta_example/settings.py
pagemeta_example/urls.py
pagemeta_example/views.py
pagemeta_example/wsgi.py
pagemeta_example/migrations/0001_initial.py
pagemeta_example/migrations/0002_blog_data.py
pagemeta_example/migrations/0003_page_meta_data.py
pagemeta_example/migrations/__init__.py
pagemeta_example/migrations/_utils.py
pagemeta_example/tests/__init__.py
pagemeta_example/tests/test_models.py
django_pagemeta-1.2.3.dist-info/METADATA
django_pagemeta-1.2.3.dist-info/WHEEL
django_pagemeta-1.2.3.dist-info/top_level.txt
django_pagemeta-1.2.3.dist-info/RECORD
