Metadata-Version: 2.1
Name: django-pagemeta
Version: 1.2.3
Summary: A simple django package for managing meta tags, og tags, images, and descriptions dynamically.
Home-page: https://github.com/aj3sh/pagemeta
Author: Ajesh Sen Thapa
Author-email: aj3sshh@gmail.com
Keywords: django meta,django page meta,meta tags,og tags,open tags,twitter card,seo,seo tags,keywords,keywords management
Classifier: Programming Language :: Python :: 3
Classifier: License :: OSI Approved :: MIT License
Classifier: Operating System :: OS Independent
